lumyn/__init__.py
lumyn/__main__.py
lumyn/assets.py
lumyn/config.py
lumyn/config_default.toml
lumyn/version.py
lumyn/_data/__init__.py
lumyn/_data/policies/lumyn-support.v0.yml
lumyn/_data/policies/starter.v1.yml
lumyn/_data/policies/packs/lumyn-account.v0.yml
lumyn/_data/policies/packs/lumyn-billing.v0.yml
lumyn/_data/schemas/decision_record.v0.schema.json
lumyn/_data/schemas/decision_record.v1.schema.json
lumyn/_data/schemas/decision_request.v0.schema.json
lumyn/_data/schemas/decision_request.v1.schema.json
lumyn/_data/schemas/interaction_ref.v0.schema.json
lumyn/_data/schemas/policy.v0.schema.json
lumyn/_data/schemas/policy.v1.schema.json
lumyn/_data/schemas/reason_codes.v0.json
lumyn/_data/schemas/reason_codes.v1.json
lumyn/_data/schemas/record_chain_refs.v1.schema.json
lumyn/api/__init__.py
lumyn/api/app.py
lumyn/api/auth.py
lumyn/api/routes_v0.py
lumyn/api/routes_v1.py
lumyn/cli/main.py
lumyn/cli/markdown.py
lumyn/cli/util.py
lumyn/cli/commands/__init__.py
lumyn/cli/commands/convert.py
lumyn/cli/commands/decide.py
lumyn/cli/commands/demo.py
lumyn/cli/commands/diff.py
lumyn/cli/commands/doctor.py
lumyn/cli/commands/explain.py
lumyn/cli/commands/export.py
lumyn/cli/commands/init.py
lumyn/cli/commands/label.py
lumyn/cli/commands/learn.py
lumyn/cli/commands/migrate.py
lumyn/cli/commands/monitor.py
lumyn/cli/commands/policy.py
lumyn/cli/commands/replay.py
lumyn/cli/commands/serve.py
lumyn/cli/commands/show.py
lumyn/core/__init__.py
lumyn/core/decide.py
lumyn/engine/consensus.py
lumyn/engine/energy.py
lumyn/engine/evaluator.py
lumyn/engine/evaluator_v1.py
lumyn/engine/normalize.py
lumyn/engine/normalize_v1.py
lumyn/engine/redaction.py
lumyn/engine/similarity.py
lumyn/memory/client.py
lumyn/memory/embed.py
lumyn/memory/types.py
lumyn/migrate/__init__.py
lumyn/migrate/v0_v1.py
lumyn/policy/__init__.py
lumyn/policy/errors.py
lumyn/policy/loader.py
lumyn/policy/spec.py
lumyn/policy/validate.py
lumyn/records/__init__.py
lumyn/records/emit.py
lumyn/records/emit_v1.py
lumyn-1.3.6.dist-info/METADATA
lumyn-1.3.6.dist-info/WHEEL
lumyn-1.3.6.dist-info/entry_points.txt
lumyn-1.3.6.dist-info/licenses/LICENSE
lumyn-1.3.6.dist-info/RECORD
