Metadata-Version: 2.4
Name: lumyn
Version: 1.3.6
Summary: Decision Records for production AI.
Project-URL: Homepage, https://github.com/davidahmann/lumyn
Project-URL: Repository, https://github.com/davidahmann/lumyn
Author: Lumyn OSS Contributors
License: Apache-2.0
License-File: LICENSE
Requires-Python: >=3.11
Requires-Dist: fastapi>=0.115
Requires-Dist: fastembed>=0.7.4
Requires-Dist: filelock>=3.20.1
Requires-Dist: jsonschema>=4.23.0
Requires-Dist: lancedb>=0.25.3
Requires-Dist: pandas>=2.3.3
Requires-Dist: pydantic>=2.7
Requires-Dist: pyyaml>=6.0.2
Requires-Dist: typer<0.20,>=0.12
Requires-Dist: ulid-py>=1.1.0
Provides-Extra: service
Requires-Dist: uvicorn>=0.30; extra == 'service'
